public_utils_jjk/__init__.py
public_utils_jjk/public_utils.py
public_utils_jjk-0.0.1.dist-info/LICENSE
public_utils_jjk-0.0.1.dist-info/METADATA
public_utils_jjk-0.0.1.dist-info/WHEEL
public_utils_jjk-0.0.1.dist-info/top_level.txt
public_utils_jjk-0.0.1.dist-info/RECORD
